tsts/__init__.py
tsts/apis.py
tsts/types.py
tsts/utils.py
tsts/cfg/__init__.py
tsts/cfg/cfg.py
tsts/cfg/defaults.py
tsts/collators/__init__.py
tsts/collators/builder.py
tsts/collators/collator.py
tsts/core/__init__.py
tsts/core/context_manager.py
tsts/core/registry.py
tsts/dataloaders/__init__.py
tsts/dataloaders/builder.py
tsts/dataloaders/dataloader.py
tsts/datasets/__init__.py
tsts/datasets/builder.py
tsts/datasets/dataset.py
tsts/loggers/__init__.py
tsts/loggers/builder.py
tsts/loggers/logger.py
tsts/losses/__init__.py
tsts/losses/builder.py
tsts/losses/dilate.py
tsts/losses/loss.py
tsts/losses/mae.py
tsts/losses/mape.py
tsts/losses/mse.py
tsts/losses/smoothmae.py
tsts/metrics/__init__.py
tsts/metrics/builder.py
tsts/metrics/mae.py
tsts/metrics/mape.py
tsts/metrics/metric.py
tsts/metrics/mse.py
tsts/metrics/rmse.py
tsts/models/__init__.py
tsts/models/builder.py
tsts/models/informer.py
tsts/models/module.py
tsts/models/nbeats.py
tsts/models/scinet.py
tsts/models/seq2seq.py
tsts/models/localscalers/__init__.py
tsts/models/localscalers/ar.py
tsts/models/localscalers/builder.py
tsts/models/localscalers/hi.py
tsts/models/localscalers/laststep.py
tsts/models/localscalers/noop.py
tsts/optimizers/__init__.py
tsts/optimizers/adam.py
tsts/optimizers/adamw.py
tsts/optimizers/builder.py
tsts/optimizers/optimizer.py
tsts/optimizers/sam.py
tsts/optimizers/sgd.py
tsts/scalers/__init__.py
tsts/scalers/builder.py
tsts/scalers/identity.py
tsts/scalers/minmax.py
tsts/scalers/scaler.py
tsts/scalers/standard.py
tsts/schedulers/__init__.py
tsts/schedulers/builder.py
tsts/schedulers/cosine.py
tsts/schedulers/cosinewithrestarts.py
tsts/schedulers/expdecay.py
tsts/schedulers/identity.py
tsts/schedulers/scheduler.py
tsts/schedulers/step.py
tsts/solvers/__init__.py
tsts/solvers/forecaster.py
tsts/solvers/solver.py
tsts/thirdparty/__init__.py
tsts/thirdparty/dilate/__init__.py
tsts/thirdparty/dilate/path_soft_dtw.py
tsts/thirdparty/dilate/soft_dtw.py
tsts/thirdparty/sam/__init__.py
tsts-1.1.3.dist-info/LICENSE
tsts-1.1.3.dist-info/METADATA
tsts-1.1.3.dist-info/WHEEL
tsts-1.1.3.dist-info/top_level.txt
tsts-1.1.3.dist-info/RECORD
