Metadata-Version: 2.1
Name: tsts
Version: 1.1.3
Summary: toolset for time series forecasting
Home-page: https://github.com/TakuyaShintate/tsts
Author: Takuya Shintate
Author-email: kmdbn2hs@gmail.com
License: MIT License
Keywords: tsts
Platform: UNKNOWN
License-File: LICENSE
Requires-Dist: numpy
Requires-Dist: torch
Requires-Dist: tqdm
Requires-Dist: yacs
Requires-Dist: numba
Requires-Dist: seaborn
Requires-Dist: terminaltables
